{
  "title_uk": "Міжнародне 1-on-1 менторство OSINT-фахівців",
  "title_en": "International 1-on-1 OSINT mentoring",
  "date": "2026-05-01T00:00:00.000Z",
  "format_uk": "Персональне менторство · 1-on-1",
  "format_en": "Personal 1-on-1 mentoring",
  "audience_uk": "7 менті · 4 країни (США, Єгипет, Ізраїль, Індія)",
  "audience_en": "7 mentees · 4 countries (USA, Egypt, Israel, India)",
  "location_uk": "Онлайн · глобально",
  "location_en": "Online · global",
  "topic_uk": "Telegram-розслідування · SOCMINT-техніки · крос-платформна атрибуція · pivot-chains",
  "topic_en": "Telegram investigations · SOCMINT techniques · cross-platform attribution · pivot-chains",
  "description_uk": "Персональне менторство OSINT-практиків з різних країн, які самостійно вийшли на зв'язок після моїх публікацій. Найпомітніше — робота з **Claire Roise (Brightrock Intel, США)**: розібрали Telegram-розслідування у форматі Zoom-сесії, згодом Claire залишила публічну рекомендацію, що ця сесія була «extremely high value». Аналогічні 1-on-1 сесії — з фахівцями з Єгипту, Ізраїлю та чотирма з Індії, які писали в особисті з питаннями і отримували повний технічний розбір їхніх кейсів. Оплата — на вибір, здебільшого добровільна.",
  "description_en": "Personal mentoring of OSINT practitioners from different countries who reached out after my publications. Most visible — work with **Claire Roise (Brightrock Intel, USA)**: we covered Telegram investigations in a Zoom session; Claire later left a public recommendation calling the session «extremely high value». Similar 1-on-1 sessions — with specialists from Egypt, Israel, and four from India, who wrote directly with questions and received full technical walkthroughs of their cases. Payment — optional, mostly voluntary.",
  "link": "recommendations.html",
  "link_label_uk": "Читати рекомендацію Claire",
  "link_label_en": "Read Claire's recommendation",
  "image": "",
  "order": 2,
  "published": true
}
